txt_hours.py
txt_hours-0.2.0.dist-info/entry_points.txt
txt_hours-0.2.0.dist-info/LICENSE
txt_hours-0.2.0.dist-info/WHEEL
txt_hours-0.2.0.dist-info/METADATA
txt_hours-0.2.0.dist-info/RECORD
