Metadata-Version: 2.1
Name: txt-hours
Version: 0.2.0
Summary: 
Author: Andrew Simmons
Author-email: agsimmons0@gmail.com
Requires-Python: >=3.6.1,<4.0.0
Classifier: Programming Language :: Python :: 3
Classifier: Programming Language :: Python :: 3.7
Classifier: Programming Language :: Python :: 3.8
Classifier: Programming Language :: Python :: 3.9
Requires-Dist: pandas (==1.1.5)
